{
  "/page": "app/page.js",
  "/catalogo/delivery/[apelido]/page": "app/catalogo/delivery/[apelido]/page.js",
  "/api/catalogo/publico/[apelido]/route": "app/api/catalogo/publico/[apelido]/route.js",
  "/api/catalogo/categorias/route": "app/api/catalogo/categorias/route.js",
  "/(dashboard)/settings/page": "app/(dashboard)/settings/page.js",
  "/(dashboard)/produtos/page": "app/(dashboard)/produtos/page.js",
  "/(dashboard)/pedidos/page": "app/(dashboard)/pedidos/page.js",
  "/(dashboard)/logistica/page": "app/(dashboard)/logistica/page.js"
}